aBASE/__init__.py
aBASE/__main__.py
aBASE/tests/__init__.py
aBASE/tests/test_1984.py
aBASE-0.0.0.dev0.dist-info/LICENSE.txt
aBASE-0.0.0.dev0.dist-info/METADATA
aBASE-0.0.0.dev0.dist-info/WHEEL
aBASE-0.0.0.dev0.dist-info/top_level.txt
aBASE-0.0.0.dev0.dist-info/RECORD
