Metadata-Version: 2.1
Name: aBASE
Version: 0.0.0.dev0
Summary: aBASE
Author-email: Johannes <johannes-programming@mailfence.com>
License: The MIT License (MIT)
Project-URL: Documentation, https://pypi.org/project/aBASE
Project-URL: Download, https://pypi.org/project/aBASE/#files
Project-URL: Source, https://github.com/johannes-programming/aBASE
Classifier: Development Status :: 1 - Planning
Classifier: License :: OSI Approved :: MIT License
Classifier: Programming Language :: Python
Classifier: Programming Language :: Python :: 3
Classifier: Programming Language :: Python :: 3 :: Only
Requires-Python: >=3.12.7
License-File: LICENSE.txt
